setup.cfg
setup.py
sigma/__init__.py
sigma.standard.egg-info/PKG-INFO
sigma.standard.egg-info/SOURCES.txt
sigma.standard.egg-info/dependency_links.txt
sigma.standard.egg-info/namespace_packages.txt
sigma.standard.egg-info/requires.txt
sigma.standard.egg-info/top_level.txt
sigma.standard.egg-info/zip-safe
sigma/standard/__init__.py
sigma/standard/error.py
sigma/standard/field.py
test/test_field.py