Metadata-Version: 1.0
Name: sigma.standard
Version: 0.2.0a0
Summary: Validation framework.
Home-page: https://github.com/pysigma/standard
Author: Suzuki Shunsuke
Author-email: suzuki.shunsuke.1989@gmail.com
License: MIT
Keywords: validation
Platform: UNKNOWN
